MANIFEST.in
README.md
requirements.txt
setup.py
Configo.egg-info/PKG-INFO
Configo.egg-info/SOURCES.txt
Configo.egg-info/dependency_links.txt
Configo.egg-info/requires.txt
Configo.egg-info/top_level.txt
bin/configo
configo/__init__.py
configo/configo.py