Metadata-Version: 1.1
Name: Configo
Version: 1.4
Summary: Easy way to use existing JSON, XML or YAML config files from bash shell/scripts
Home-page: http://m.ignev.net/code/configo
Author: Marian Ignev
Author-email: m@ignev.net
License: UNKNOWN
Platform: UNKNOWN
Classifier: Development Status :: 4 - Beta
Classifier: Operating System :: POSIX
Classifier: Operating System :: POSIX :: BSD
Classifier: Operating System :: POSIX :: Linux
Classifier: Operating System :: Unix
Classifier: Programming Language :: Python
Classifier: Programming Language :: Python :: 2
Classifier: Programming Language :: Python :: 2.7
Classifier: Topic :: System :: Shells
Classifier: Topic :: Text Processing :: Markup :: XML
Classifier: Topic :: Utilities
